<?xml version="1.0" encoding="UTF-8"?>
<QF id="AIF Industry Concepts_4" sectionNumber="" articleNumber="0" articleName="">
    <question>
        <text><![CDATA[The maximum number of investors permitted in a single AIF scheme is:]]></text>
        <answers>
            <answer correct="no"><text><![CDATA[100]]></text></answer>
            <answer correct="no"><text><![CDATA[500]]></text></answer>
            <answer correct="yes"><text><![CDATA[1,000]]></text></answer>
            <answer correct="no"><text><![CDATA[Unlimited]]></text></answer>
        </answers>
        <explanation><text><![CDATA[**The Logic:** As per SEBI (AIF) Regulations, the maximum number of investors in a single scheme shall not exceed 1,000. This cap maintains the 'private' character of the fund and distinguishes it from public pooling vehicles like mutual funds.
**The Trap:** This is per scheme, not per fund. An AIF can have multiple schemes, each with up to 1,000 investors. With a minimum of INR 1 crore per investor and maximum 1,000 investors, the theoretical maximum scheme size is INR 1,000 crore from the minimum commitments alone.
**Cross-Exam Context:** The investor cap is a defining feature of AIFs versus mutual funds (unlimited investors). This distinction is tested in XIX-A and Series V-A.
**Distributor's Pro-Tip:** The 1,000 investor cap means AIFs must be selective about their investor base. As a distributor, focus on quality over quantity — identify investors who truly understand alternative investments and can commit for the long term.]]></text></explanation>
    </question>
</QF>