<?xml version="1.0" encoding="UTF-8"?>
<QF id="AIF Investment Process and Governance_8" sectionNumber="" articleNumber="0" articleName="">
    <question>
        <text><![CDATA[A Shareholders' Agreement (SHA) in a PE/VC investment typically governs:]]></text>
        <answers>
            <answer correct="no"><text><![CDATA[Only the voting rights of shareholders]]></text></answer>
            <answer correct="yes"><text><![CDATA[The relationship between shareholders including rights, obligations, transfer restrictions, and governance matters]]></text></answer>
            <answer correct="no"><text><![CDATA[Only the dividend distribution policy]]></text></answer>
            <answer correct="no"><text><![CDATA[The employment terms of company employees]]></text></answer>
        </answers>
        <explanation><text><![CDATA[**The Logic:** The SHA is a comprehensive agreement governing the relationship between shareholders. It covers governance (board composition, voting), transfer restrictions (lock-in, ROFR, tag/drag along), information rights, anti-dilution, reserved matters requiring investor consent, and exit mechanisms.
**The Trap:** The SHA is different from the Articles of Association — the SHA is a private contract between specific shareholders and may contain provisions not in the public articles.
**Cross-Exam Context:** SHA terms are tested in XIX-A Chapter 7 and Chapter 9.
**Distributor's Pro-Tip:** The SHA is one of the most important documents in PE/VC investing. Strong SHA terms protect AIF investors' interests. Evaluate whether the fund manager has negotiated robust SHA protections.]]></text></explanation>
    </question>
</QF>