<?xml version='1.0' encoding='UTF-8'?>
<QF id="AML_CFT_Guidelines_10" sectionNumber="" articleNumber="0" articleName="">
    <question><text><![CDATA[Under the PML Rules, the Central KYC Records Registry was required to be set up within how many days of the coming into force of the PML (Maintenance of Records) Amendment Rules, 2015?]]></text>
        <answers>
            <answer correct="no"><text><![CDATA[90 days]]></text></answer>
            <answer correct="no"><text><![CDATA[120 days]]></text></answer>
            <answer correct="yes"><text><![CDATA[180 days]]></text></answer>
            <answer correct="no"><text><![CDATA[365 days]]></text></answer>
        </answers>
        <explanation><text><![CDATA[**The Logic:** Rule 9A(1) states that the Central Government shall within a period of 180 days from the date of coming into force of the PML (Maintenance of Records) Amendment Rules, 2015, set up a Central KYC Records Registry for the purpose of receiving, storing, safeguarding and retrieving electronic copies of KYC records.

**The Trap:** 180 days appears in two contexts in PMLA: provisional attachment of property under Section 5, and setting up CKYCR under Rule 9A. The exam may test either. Here it is specifically about the CKYCR setup timeline.

**Cross-Exam Context:** This is a sample question in the NISM XXIV workbook. The Central KYC Records Registry (CKYCR) issues a KYC Identifier for each client, which is communicated to the client by the reporting entity.

**Distributor's Pro-Tip:** CKYCR eliminates duplicate KYC for clients across financial entities. Once KYC is done with one reporting entity and uploaded to CKYCR, other entities can retrieve it using the KYC Identifier — reducing client burden and improving efficiency.]]></text></explanation>
    </question>
</QF>