<?xml version="1.0" encoding="UTF-8"?>
<QF id="Custodians Compliance_46" sectionNumber="" articleNumber="0" articleName="">
    <question>
        <text><![CDATA[Under SEBI (Custodian) Regulations, 1996, how often shall a custodian have its mechanisms for controls, systems, procedures, and safeguards inspected?]]></text>
        <answers>
            <answer correct="no"><text><![CDATA[Quarterly by an internal auditor]]></text></answer>
            <answer correct="no"><text><![CDATA[Half-yearly by a SEBI-appointed inspector]]></text></answer>
            <answer correct="yes"><text><![CDATA[Annually by an expert, and the inspection report shall be forwarded to SEBI within three months from the date of inspection]]></text></answer>
            <answer correct="no"><text><![CDATA[Once every three years by an independent auditor]]></text></answer>
        </answers>
        <explanation><text><![CDATA[**The Logic:** Every custodian shall have the mechanisms inspected annually by an expert and shall forward the inspection report to SEBI within three months from the date of inspection.
**The Trap:** The three-month timeline for forwarding the report is an important detail -- just conducting the inspection is not enough; timely submission to SEBI is mandatory.
**Cross-Exam Context:** Inspection and audit requirements for custodians are tested in NISM Series III-A exam.
**Distributor's Pro-Tip:** Engage the expert well before the financial year-end to allow sufficient time for inspection, report preparation, and submission within the three-month window.]]></text></explanation>
    </question>
</QF>