<?xml version="1.0" encoding="UTF-8"?>
<QF id="Evaluating Fund Performance and Fund Selection_40" sectionNumber="" articleNumber="0" articleName="">
    <question>
        <text><![CDATA[Which of the following is the most appropriate benchmark for a debt mutual fund investing in corporate bonds?]]></text>
        <answers>
            <answer correct="no"><text><![CDATA[BSE Sensex]]></text></answer>
            <answer correct="no"><text><![CDATA[NSE Nifty 50]]></text></answer>
            <answer correct="no"><text><![CDATA[Gold price index]]></text></answer>
            <answer correct="yes"><text><![CDATA[CRISIL Composite Bond Index]]></text></answer>
        </answers>
        <explanation><text><![CDATA[**The Logic:** Benchmarks must reflect the fund's asset class. A corporate bond fund should be benchmarked against a bond index like CRISIL Composite Bond Index, not equity indices.
**The Trap:** Candidates may select equity benchmarks (Sensex, Nifty) out of familiarity, but these are inappropriate for debt funds.
**Cross-Exam Context:** SEBI requires funds to select benchmarks that accurately represent their investment universe. CRISIL provides various bond indices for different debt fund categories.
**Distributor's Pro-Tip:** When evaluating debt funds, ensure you are comparing against the right benchmark. A corporate bond fund beating Sensex is meaningless — compare it against the relevant CRISIL bond index.]]></text></explanation>
    </question>
</QF>