<?xml version="1.0" encoding="UTF-8"?>
<QF id="Exempt Incomes, Deductions, Rebates_11" sectionNumber="" articleNumber="0" articleName="">
    <question>
        <text><![CDATA[An individual investor redeems Sovereign Gold Bonds (SGBs) upon maturity. What is the tax treatment of the capital gains arising on such redemption?]]></text>
        <answers>
            <answer correct="no"><text><![CDATA[Taxable as long-term capital gains at 20% with indexation benefit]]></text></answer>
            <answer correct="no"><text><![CDATA[Taxable as long-term capital gains at 12.5% without indexation]]></text></answer>
            <answer correct="yes"><text><![CDATA[Fully exempt from capital gains tax]]></text></answer>
            <answer correct="no"><text><![CDATA[Taxable as short-term capital gains at applicable slab rates]]></text></answer>
        </answers>
        <explanation><text><![CDATA[**The Logic:** Capital gains arising on redemption of Sovereign Gold Bonds (SGBs) by an individual are fully exempt from tax. This exemption applies only on maturity redemption (8 years) — not on secondary market sale or premature redemption through RBI's buyback window. Note that the 2.5% annual interest on SGBs remains taxable.
**The Trap:** Options A and B apply capital gains tax rates that would be relevant for physical gold or gold ETFs, not for SGB redemption. Option D incorrectly classifies the gains as short-term.
**Cross-Exam Context:** NISM Series X-A and Series V-A exams compare tax treatment of SGBs versus gold ETFs and physical gold — a frequent exam topic.
**Distributor's Pro-Tip:** SGBs offer triple benefits: 2.5% annual interest, capital gains exemption on maturity, and no storage/purity concerns — making them the most tax-efficient way to hold gold for long-term investors.]]></text></explanation>
    </question>
</QF>
