<?xml version="1.0" encoding="UTF-8"?>
<QF id="Fraudulent and Unfair Trade Practices_17" sectionNumber="" articleNumber="0" articleName="">
    <question>
        <text><![CDATA[As per the Supreme Court findings, to establish charges of tippee trading under Regulations 3(a), (b), (c), (d) and 4(1) of FUTP 2003, which of the following must be proven?]]></text>
        <answers>
            <answer correct="no"><text><![CDATA[Only that there was a family relationship between the tipper and the tippee]]></text></answer>
            <answer correct="no"><text><![CDATA[Only that the tippee's trades matched with the institutional trades]]></text></answer>
            <answer correct="yes"><text><![CDATA[That the tipper had a duty to keep non-public information confidential, the breach was known to the tippee, and the tippee still traded thereby defrauding the person whose orders were front-run]]></text></answer>
            <answer correct="no"><text><![CDATA[Only that the tippee made a profit from the trades]]></text></answer>
        </answers>
        <explanation><text><![CDATA[**The Logic:** The Supreme Court stated that to establish tippee trading charges, one needs to prove: (1) the tipper was under a duty to keep non-public information confidential, (2) such breach of duty was known to the tippee, and (3) the tippee still traded thereby defrauding the person whose orders were front-run.
**The Trap:** Simply making a profit or having a family relationship is insufficient - there must be proof of knowledge of breach of duty.
**Cross-Exam Context:** This three-part test for tippee trading is also relevant for NISM Series VIII and NISM Series III-B.
**Distributor's Pro-Tip:** The burden of proof requires establishing both the tipper's duty breach AND the tippee's knowledge of that breach.]]></text></explanation>
    </question>
</QF>