<?xml version="1.0" encoding="UTF-8"?>
<QF id="III-C Prevention of Money Laundering Act_14" sectionNumber="" articleNumber="0" articleName="">
    <question>
        <text><![CDATA[Who is responsible for timely submission of CTR, STR, and NTR to FIU-IND?]]></text>
        <answers>
            <answer correct="no"><text><![CDATA[Designated Director]]></text></answer>
            <answer correct="yes"><text><![CDATA[Principal Officer]]></text></answer>
            <answer correct="no"><text><![CDATA[Internal Auditor]]></text></answer>
            <answer correct="no"><text><![CDATA[Compliance Officer]]></text></answer>
        </answers>
        <explanation><text><![CDATA[**The Logic:** As per Section 9.3.10(d), the Principal Officer will be responsible for timely submission of CTR, STR and NTR to FIU-IND.
**The Trap:** While the Designated Director has overall compliance responsibility, the operational responsibility for report submission lies with the Principal Officer.
**Distributor's Pro-Tip:** The Principal Officer should be an officer at the management level and acts as a central reference point for suspicious transaction reporting.]]></text></explanation>
    </question>
</QF>