<?xml version="1.0" encoding="UTF-8"?>
<QF id="Introduction to Merchant Banking_11" sectionNumber="" articleNumber="0" articleName="">
    <question>
        <text><![CDATA[Under Section 15HA of the SEBI Act, the maximum penalty for fraudulent and unfair trade practices is:]]></text>
        <answers>
            <answer correct="no"><text><![CDATA[Rs. 10 crore]]></text></answer>
            <answer correct="no"><text><![CDATA[Rs. 15 crore]]></text></answer>
            <answer correct="yes"><text><![CDATA[Rs. 25 crore or three times the profits made, whichever is higher]]></text></answer>
            <answer correct="no"><text><![CDATA[Rs. 50 crore]]></text></answer>
        </answers>
        <explanation><text><![CDATA[**The Logic:** Section 15HA prescribes a penalty with a minimum of Rs. 5 lakh and a maximum of Rs. 25 crore or three times the profits made from the fraudulent practice, whichever is higher. This ensures the penalty always exceeds the ill-gotten gains.
**The Trap:** The "or three times the profits" clause is critical — candidates who only remember the Rs. 25 crore cap might think it is a fixed maximum, but the penalty can actually exceed Rs. 25 crore if 3x profits is higher.
**Cross-Exam Context:** Penalty provisions under the SEBI Act are tested across NISM Series VIII, XII, and XV certifications.
**Distributor's Pro-Tip:** The "3x profits" mechanism is a disgorgement-plus concept — it ensures that fraud never pays. The same structure (Rs. 25 crore or 3x profits) applies to both insider trading (15G) and non-disclosure of acquisition (15H).]]></text></explanation>
    </question>
</QF>
