<?xml version='1.0' encoding='UTF-8'?>
<QF id="IV Interest Rate Futures_89" sectionNumber="" articleNumber="0" articleName="">
    <question><text><![CDATA[Under RBI guidelines, which institutions have specific norms for participation in IRF?]]></text>
        <answers>
            <answer correct="yes"><text><![CDATA[Scheduled Commercial Banks, Primary Dealers, and other RBI-regulated entities]]></text></answer>
            <answer correct="no"><text><![CDATA[Only Foreign Portfolio Investors]]></text></answer>
            <answer correct="no"><text><![CDATA[Only mutual funds and insurance companies]]></text></answer>
            <answer correct="no"><text><![CDATA[Only retail individual investors]]></text></answer>
        </answers>
        <explanation><text><![CDATA[**The Logic:** RBI has issued specific guidelines for Scheduled Commercial Banks, Primary Dealers, and other entities under its regulatory purview regarding their participation in IRF. These norms cover position limits, reporting requirements, and risk management.

**The Trap:** FPIs, mutual funds, and insurance companies participate under SEBI norms, not RBI norms. Retail investors don't have specific RBI norms. The joint regulation means RBI oversees banking system participants while SEBI oversees other market participants.

**Cross-Exam Context:** The SEBI-RBI regulatory divide is: RBI regulates banks and PDs in IRF; SEBI regulates exchanges, trading members, and other participants. This dual framework is unique to India's IRF market.

**Distributor's Pro-Tip:** Banks must maintain positions within RBI-prescribed limits and report their IRF activity. RBI monitors banks' derivatives activity to ensure it doesn't create systemic risk. Banks can use IRF for both hedging and trading purposes.]]></text></explanation>
    </question>
</QF>