<?xml version="1.0" encoding="UTF-8"?>
<QF id="Regulatory Requirements for Research Analysts_79" sectionNumber="" articleNumber="0" articleName="">
    <question>
        <text><![CDATA[Regulation 15A allowing research analysts to charge fees was introduced to:]]></text>
        <answers>
            <answer correct="no"><text><![CDATA[Increase the cost of research for investors]]></text></answer>
            <answer correct="yes"><text><![CDATA[Enable a fee-based research model that reduces dependence on brokerage revenue and potential conflicts]]></text></answer>
            <answer correct="no"><text><![CDATA[Force all investors to pay for research]]></text></answer>
            <answer correct="no"><text><![CDATA[Eliminate free research entirely from the market]]></text></answer>
        </answers>
        <explanation><text><![CDATA[**The Logic:** Fee-based research aligns analyst incentives with research quality rather than brokerage generation, reducing conflicts of interest.
**The Trap:** The regulation enables, not mandates, fee charging. It provides an alternative business model with fewer inherent conflicts.
**Cross-Exam Context:** Ch 14 NISM XV.
**Distributor's Pro-Tip:** Fee-based research is growing globally as regulators (MiFID II in Europe, SEBI in India) push for unbundling of research from execution services.]]></text></explanation>
    </question>
</QF>