<?xml version="1.0" encoding="UTF-8"?>
<QF id="Regulatory Requirements for Research Analysts_18" sectionNumber="" articleNumber="0" articleName="">
    <question>
        <text><![CDATA[Research analyst registration under SEBI regulations requires:]]></text>
        <answers>
            <answer correct="no"><text><![CDATA[No qualification or certification]]></text></answer>
            <answer correct="yes"><text><![CDATA[NISM Series XV certification as one of the eligibility requirements]]></text></answer>
            <answer correct="no"><text><![CDATA[Only a graduate degree in any subject]]></text></answer>
            <answer correct="no"><text><![CDATA[Only 10 years of market experience]]></text></answer>
        </answers>
        <explanation><text><![CDATA[**The Logic:** SEBI requires NISM Series XV certification for associated persons of research analysts under Regulation 7(2).
**The Trap:** Certification is mandatory, not optional. While other qualifications may also be required, NISM XV is specifically mentioned.
**Cross-Exam Context:** Ch 14 NISM XV.
**Distributor's Pro-Tip:** NISM XV certification must be renewed periodically through CPE programs. Lapsed certification can result in regulatory action.]]></text></explanation>
    </question>
</QF>