<?xml version="1.0" encoding="UTF-8"?>
<QF id="Retirement Planning Products: National Pension System (NPS)_56" sectionNumber="" articleNumber="0" articleName="">
    <question>
        <text><![CDATA[Once an NPS annuity is purchased, can the subscriber change the annuity option or ASP?]]></text>
        <answers>
            <answer correct="no"><text><![CDATA[Yes, after 5 years]]></text></answer>
            <answer correct="no"><text><![CDATA[Yes, once every year]]></text></answer>
            <answer correct="yes"><text><![CDATA[No, the choice is irreversible]]></text></answer>
            <answer correct="no"><text><![CDATA[Yes, with PFRDA approval]]></text></answer>
        </answers>
        <explanation><text><![CDATA[**The Logic:** Once an annuity is purchased from an ASP, the subscriber cannot change the annuity option or the ASP. The choice is permanent and irreversible.
**The Trap:** Some candidates assume annuity portability exists similar to PFM changes. Annuity purchase is a one-time, final decision.
**Cross-Exam Context:** This irreversibility makes the annuity decision the most critical choice in the NPS journey. It affects retirement income for life.
**Distributor's Pro-Tip:** Spend significant time helping clients evaluate annuity options before purchase. Use annuity calculators to compare income streams.]]></text></explanation>
    </question>
</QF>