<?xml version="1.0" encoding="UTF-8"?>
<QF id="Retirement Planning Products: National Pension System (NPS)_82" sectionNumber="" articleNumber="0" articleName="">
    <question>
        <text><![CDATA[Which of the following is NOT a function of the CRA in the NPS ecosystem?]]></text>
        <answers>
            <answer correct="no"><text><![CDATA[Maintaining subscriber records]]></text></answer>
            <answer correct="no"><text><![CDATA[Issuing PRAN cards]]></text></answer>
            <answer correct="yes"><text><![CDATA[Investing subscriber funds per PFRDA guidelines]]></text></answer>
            <answer correct="no"><text><![CDATA[Providing account maintenance services]]></text></answer>
        </answers>
        <explanation><text><![CDATA[**The Logic:** Investing subscriber funds is the function of Pension Fund Managers (PFMs), not the CRA. CRA handles record-keeping, PRAN issuance, and account maintenance.
**The Trap:** CRA and PFM functions are often confused. CRA = record-keeping, PFM = investment management.
**Cross-Exam Context:** CRA functions: records, PRAN, account maintenance, SOT. PFM functions: investing, NAV declaration, portfolio management.
**Distributor's Pro-Tip:** Direct clients to the CRA for account queries and to PFM performance reports for investment-related decisions.]]></text></explanation>
    </question>
</QF>