<?xml version="1.0" encoding="UTF-8"?>
<QF id="VB Investor Services_8" sectionNumber="" articleNumber="0" articleName="">
    <question><text><![CDATA[What is a Systematic Transfer Plan (STP)?]]></text>
        <answers>
            <answer correct="no"><text><![CDATA[A plan to transfer money from a mutual fund to a bank account regularly]]></text></answer>
            <answer correct="yes"><text><![CDATA[A facility to transfer a fixed amount at regular intervals from one mutual fund scheme to another within the same fund house]]></text></answer>
            <answer correct="no"><text><![CDATA[A plan to transfer units between two different investors]]></text></answer>
            <answer correct="no"><text><![CDATA[A transfer of units from Regular Plan to Direct Plan]]></text></answer>
        </answers>
        <explanation><text><![CDATA[**The Logic:** STP (Systematic Transfer Plan) allows an investor to transfer a fixed amount at regular intervals from one scheme to another scheme within the same mutual fund house. Typically, investors park a lump sum in a liquid or debt fund and then set up an STP to transfer a fixed amount monthly to an equity fund. This gives the benefit of rupee cost averaging.
**The Trap:** STP works only within the same fund house (AMC). You cannot do an STP from one AMC's scheme to another AMC's scheme. Also, each transfer is treated as a redemption from the source scheme and a purchase in the target scheme, with applicable tax implications.
**Cross-Exam Context:** Also tested in V-A.
**Distributor's Pro-Tip:** For retired investors with a lump sum (like a retirement gratuity), STP is an excellent strategy. They can park the money in a liquid fund and set up an STP to gradually move it into an equity or balanced fund over 6-12 months.]]></text></explanation>
    </question>
</QF>
