<?xml version="1.0" encoding="UTF-8"?>
<QF id="VI Transmission and Nomination_4" sectionNumber="" articleNumber="0" articleName="">
    <question>
        <text><![CDATA[In a joint demat account, who must sign the nomination form?]]></text>
        <answers>
            <answer correct="yes"><text><![CDATA[All joint holders]]></text></answer>
            <answer correct="no"><text><![CDATA[Only the first holder]]></text></answer>
            <answer correct="no"><text><![CDATA[Any one joint holder]]></text></answer>
            <answer correct="no"><text><![CDATA[Only the holder with the largest shareholding]]></text></answer>
        </answers>
        <explanation><text><![CDATA[**The Logic:** If the account is held jointly, all joint holders will be required to sign the nomination form.
**The Trap:** 'Only the first holder' is incorrect — nomination is a serious disposition and requires consent of all holders.
**Cross-Exam Context:** Series V-A covers joint holder nomination requirements for mutual funds.
**Distributor's Pro-Tip:** This unanimity requirement protects all joint holders. One holder cannot unilaterally decide who receives the securities on death.]]></text></explanation>
    </question>
</QF>