<?xml version='1.0' encoding='UTF-8'?>
<QF id="VII Clearing Process_70" sectionNumber="" articleNumber="0" articleName="">
    <question><text><![CDATA[For FPIs, allocation of INST trades is allowed only to:]]></text>
        <answers>
            <answer correct="yes"><text><![CDATA[Related FPIs, whose details can be provided to the Clearing Corporation]]></text></answer>
            <answer correct="no"><text><![CDATA[Any FPI registered with SEBI]]></text></answer>
            <answer correct="no"><text><![CDATA[Only Category I FPIs]]></text></answer>
            <answer correct="no"><text><![CDATA[Any institutional investor]]></text></answer>
        </answers>
        <explanation><text><![CDATA[**The Logic:** Members can provide details of related FPIs to the CC, and INST trade allocation is only to related FPIs.
**The Trap:** The restriction to related FPIs prevents misuse of the INST code for unrelated entities.
**Cross-Exam Context:** Related FPI identification is important for operational compliance.
**Distributor's Pro-Tip:** Members must maintain and update the list of related FPIs with the clearing corporation.]]></text></explanation>
    </question>
</QF>