<?xml version='1.0' encoding='UTF-8'?>
<QF id="VII Investor Grievances and Arbitration_34" sectionNumber="" articleNumber="0" articleName="">
    <question><text><![CDATA[If the Market Participant wants to challenge an arbitral award, it must deposit with the MII:]]></text>
        <answers>
            <answer correct="yes"><text><![CDATA[100% of the amounts payable in terms of the arbitral award]]></text></answer>
            <answer correct="no"><text><![CDATA[50% of the amounts payable]]></text></answer>
            <answer correct="no"><text><![CDATA[25% of the amounts payable]]></text></answer>
            <answer correct="no"><text><![CDATA[No deposit is required for challenge]]></text></answer>
        </answers>
        <explanation><text><![CDATA[**The Logic:** The Market Participant must deposit 100% of amounts payable before challenging the award.
**The Trap:** This is designed to prevent frivolous challenges that delay payment to investors.
**Cross-Exam Context:** The full deposit requirement ensures the investor's money is secured even during challenge.
**Distributor's Pro-Tip:** Failure to deposit may result in consequences determined by the Stock Exchange.]]></text></explanation>
    </question>
</QF>