<?xml version='1.0' encoding='UTF-8'?>
<QF id="XA Operations Regulation and Ethics_55" sectionNumber="" articleNumber="0" articleName="">
    <question><text><![CDATA[Under the Investor Charter provisions effective June 2025, by what date of each month must a SEBI-registered investment adviser disclose complaint data on their website?]]></text>
        <answers>
            <answer correct="no"><text><![CDATA[By the 15th of the next month]]></text></answer>
            <answer correct="yes"><text><![CDATA[By the 7th of the next month]]></text></answer>
            <answer correct="no"><text><![CDATA[By the last working day of the same month]]></text></answer>
            <answer correct="no"><text><![CDATA[By the 10th of the next month]]></text></answer>
        </answers>
        <explanation><text><![CDATA[**The Logic:** Under the Investor Charter provisions (effective June 2025), SEBI-registered investment advisers must disclose monthly complaint data on their website by the 7th of the following month. Additionally, the Investor Charter must be disclosed on the IA's website and provided to clients during onboarding.

**The Trap:** The 7th is a specific date that is easy to confuse with the 10th or 15th, which are common deadlines for other regulatory filings (e.g., GST, TDS). The Investor Charter deadline is distinctly the 7th.

**Cross-Exam Context:** Investor Charter requirements are relatively new (June 2025) and are specifically tested in NISM Series X-A. Similar charter obligations may extend to other intermediaries over time.

**Distributor's Pro-Tip:** Automate your complaint data disclosure process. Set a recurring calendar reminder for the 5th of each month to prepare and upload complaint data, giving yourself a 2-day buffer before the 7th deadline.]]></text></explanation>
    </question>
</QF>
