<?xml version='1.0' encoding='UTF-8'?>
<QF id="XVI Commodity Indices_11" sectionNumber="" articleNumber="0" articleName="">
    <question>
        <text><![CDATA[The maximum tenor of a Commodity Index Futures contract as per SEBI regulations is:]]></text>
        <answers>
            <answer correct="yes"><text><![CDATA[12 months]]></text></answer>
            <answer correct="no"><text><![CDATA[3 months]]></text></answer>
            <answer correct="no"><text><![CDATA[6 months]]></text></answer>
            <answer correct="no"><text><![CDATA[24 months]]></text></answer>
        </answers>
        <explanation><text><![CDATA[**The Logic:** The maximum tenor of a Commodity Index Futures contract shall not exceed 12 months.
**The Trap:** While most active trading occurs in near-month contracts, the maximum allowed tenor is 12 months, not shorter periods.
**Cross-Exam Context:** Series VIII covers expiry cycles for equity index futures (typically monthly expiry).
**Distributor's Pro-Tip:** Most liquidity concentrates in near-month contracts — longer-dated commodity index futures may have wider spreads and lower volume.]]></text></explanation>
    </question>
</QF>