<?xml version='1.0' encoding='UTF-8'?>
<QF id="XVI Introduction to Commodity Markets_12" sectionNumber="" articleNumber="0" articleName="">
    <question>
        <text><![CDATA[What is the full form of eNAM?]]></text>
        <answers>
            <answer correct="yes"><text><![CDATA[Electronic National Agriculture Market]]></text></answer>
            <answer correct="no"><text><![CDATA[Electronic National Asset Management]]></text></answer>
            <answer correct="no"><text><![CDATA[Electronic Network for Agricultural Marketing]]></text></answer>
            <answer correct="no"><text><![CDATA[Electronic National Agricultural Mandi]]></text></answer>
        </answers>
        <explanation><text><![CDATA[**The Logic:** eNAM stands for Electronic National Agriculture Market. It is a Pan-India electronic trading portal networking existing APMCs to create a unified national market for agricultural commodities.
**The Trap:** The other options sound plausible but are incorrect. eNAM specifically creates a unified national market platform.
**Cross-Exam Context:** Series XII (Securities Markets Foundation) covers market infrastructure including electronic trading platforms.
**Distributor's Pro-Tip:** eNAM benefits farmers through transparent price discovery — understanding this platform helps explain how spot and derivatives markets interact in agriculture.]]></text></explanation>
    </question>
</QF>