<?xml version='1.0' encoding='UTF-8'?>
<QF id="XVI Uses of Commodity Derivatives_37" sectionNumber="" articleNumber="0" articleName="">
    <question>
        <text><![CDATA[In a backwardation market, strengthening of basis means:]]></text>
        <answers>
            <answer correct="yes"><text><![CDATA[Basis becomes more positive — spot rises further above futures, benefiting short hedgers]]></text></answer>
            <answer correct="no"><text><![CDATA[Basis becomes less positive — moving towards contango]]></text></answer>
            <answer correct="no"><text><![CDATA[Both prices converge to zero]]></text></answer>
            <answer correct="no"><text><![CDATA[The market converts to contango]]></text></answer>
        </answers>
        <explanation><text><![CDATA[**The Logic:** In backwardation (basis positive), strengthening means basis becomes more positive (spot gains further relative to futures). Short hedgers benefit.
**The Trap:** Less positive is weakening. Neither convergence to zero nor conversion to contango describes strengthening.
**Cross-Exam Context:** Basis dynamics are tested across commodity derivative exams.
**Distributor's Pro-Tip:** Agricultural backwardation often strengthens during supply disruptions — producers (short hedgers) benefit as spot prices spike higher relative to futures.]]></text></explanation>
    </question>
</QF>