<?xml version="1.0" encoding="UTF-8"?>
<QF id="XXVA Introduction to Research Analyst Framework_17" sectionNumber="" articleNumber="0" articleName="">
    <question>
        <text><![CDATA[Under the Securities Contracts (Regulation) Act, 1956, which of the following entities is primarily governed?]]></text>
        <answers>
            <answer correct="no"><text><![CDATA[Banks and financial institutions]]></text></answer>
            <answer correct="yes"><text><![CDATA[Stock exchanges, securities contracts, and listing of securities]]></text></answer>
            <answer correct="no"><text><![CDATA[Insurance companies and pension funds]]></text></answer>
            <answer correct="no"><text><![CDATA[Real estate developers and construction companies]]></text></answer>
        </answers>
        <explanation><text><![CDATA[**The Logic:** SCRA 1956 governs stock exchanges (through recognition and supervision), contracts in securities, and listing of securities on stock exchanges. It provides the legal framework for securities trading.
**The Trap:** Banks are under RBI, insurance under IRDAI, pensions under PFRDA. Real estate is outside securities regulation.
**Cross-Exam Context:** SCRA 1956 is tested across virtually all NISM exams — it's the foundational legislation for securities market structure.
**Distributor's Pro-Tip:** When research covers listed companies, SCRA provisions on listing requirements and obligations are directly relevant — understanding these helps in evaluating corporate governance quality.]]></text></explanation>
    </question>
</QF>